pelican_commonmark/__init__.py
pelican_commonmark-0.1.0.dist-info/DESCRIPTION.rst
pelican_commonmark-0.1.0.dist-info/METADATA
pelican_commonmark-0.1.0.dist-info/metadata.json
pelican_commonmark-0.1.0.dist-info/RECORD
pelican_commonmark-0.1.0.dist-info/top_level.txt
pelican_commonmark-0.1.0.dist-info/WHEEL
